screenagents/__init__.py
screenagents/basebenchmark.py
screenagents/benchmark_result.py
screenagents/chat_message.py
screenagents/registry.py
screenagents/resize_image.py
screenagents/response_generation.py
screenagents/utils.py
screenagents/agents/__init__.py
screenagents/agents/models.py
screenagents/agents/prompt.py
screenagents/agents/qwentest.py
screenagents/agents/requirements.txt
screenagents/agents/run.py
screenagents/agents/client/android_env_client.py
screenagents/agents/client/desktop_env_client.py
screenagents/agents/client/osworld_vm_downloader.py
screenagents/agents/remote_env/__init__.py
screenagents/agents/remote_env/create_remote_env.py
screenagents/agents/remote_env/provider.py
screenagents/agents/remote_env/docker/provider.py
screenagents/agents/vision_agents/android_agent.py
screenagents/agents/vision_agents/base_vision_agent.py
screenagents/agents/vision_agents/desktop_agent.py
screenagents/agents/vision_agents/e2b_agent.py
screenagents/benchmarks/hubbasebenchmark.py
screenagents/benchmarks/model.py
screenagents/benchmarks/utils.py
screenagents/benchmarks/multistep/__init__.py
screenagents/benchmarks/multistep/config.py
screenagents/benchmarks/multistep/generation.py
screenagents/benchmarks/multistep/android_world/README.md
screenagents/benchmarks/multistep/android_world/__init__.py
screenagents/benchmarks/multistep/android_world/benchmark.py
screenagents/benchmarks/multistep/android_world/config.py
screenagents/benchmarks/multistep/android_world/make_hub_dataset.py
screenagents/benchmarks/multistep/android_world/task_metadata.json
screenagents/benchmarks/multistep/browse_comp/__init__.py
screenagents/benchmarks/multistep/browse_comp/benchmark.py
screenagents/benchmarks/multistep/browse_comp/config.py
screenagents/benchmarks/multistep/browse_comp/prompts.py
screenagents/benchmarks/multistep/browse_comp/tests/test_browse_comp.py
screenagents/benchmarks/multistep/gaia/__init__.py
screenagents/benchmarks/multistep/gaia/benchmark.py
screenagents-0.0.1.dist-info/METADATA
screenagents-0.0.1.dist-info/WHEEL
screenagents-0.0.1.dist-info/licenses/LICENSE
screenagents-0.0.1.dist-info/RECORD
